synapse_test_helper/__init__.py
synapse_test_helper/py.typed
synapse_test_helper/synapse_test_helper.py
synapse_test_helper-0.1.0.dist-info/METADATA
synapse_test_helper-0.1.0.dist-info/WHEEL
synapse_test_helper-0.1.0.dist-info/licenses/LICENSE
synapse_test_helper-0.1.0.dist-info/licenses/NOTICE
synapse_test_helper-0.1.0.dist-info/RECORD
