Metadata-Version: 2.3
Name: synapse-test-helper
Version: 0.1.0
Summary: Utilities for integration tests against Synapse.
Project-URL: repository, https://github.com/ki-tools/synapse-test-helper-py
License: Apache License
License-File: LICENSE
License-File: NOTICE
Keywords: Synapse
Classifier: License :: OSI Approved :: Apache Software License
Classifier: Operating System :: OS Independent
Classifier: Programming Language :: Python
Classifier: Programming Language :: Python :: 3.8
Classifier: Programming Language :: Python :: 3.9
Classifier: Programming Language :: Python :: 3.10
Classifier: Programming Language :: Python :: 3.11
Requires-Python: >=3.8
Requires-Dist: synapseclient<3.0.0,>=2.3.1
